setup.py
anidb/__init__.py
anidb.egg-info/PKG-INFO
anidb.egg-info/SOURCES.txt
anidb.egg-info/dependency_links.txt
anidb.egg-info/requires.txt
anidb.egg-info/top_level.txt