Metadata-Version: 1.1
Name: anidb
Version: 0.0.1
Summary: AniDB API wrapper
Home-page: https://github.com/iamale/anidb.py
Author: Ale
Author-email: ale@incrowd.ws
License: MIT
Platform: UNKNOWN
Classifier: Development Status :: 2 - Pre-Alpha
Classifier: Intended Audience :: Developers
Classifier: Natural Language :: English
Classifier: License :: OSI Approved :: MIT License
Classifier: Programming Language :: Python
Classifier: Programming Language :: Python :: 2.6
Classifier: Programming Language :: Python :: 2.7
